{"_type":"export","__export_format":4,"__export_date":"2019-12-21T17:05:38.041Z","__export_source":"insomnia.desktop.app:v7.0.6","resources":[{"_id":"req_dbd63a1db8fb41c6afa59d993563c458","authentication":{"token":"{{ token  }}","type":"bearer"},"body":{"mimeType":"application/json","text":"{\n\t\"DataNascimento\": \"1983-11-12\",\n\"Email\": \"ricardotao@gmail.com\",\n\"Endereco\": {\n\t\"Logradouro\": \"Rua Serra Redonda\", \n\t\"Numero\": 0, \n\t\"Complemento\": \"\", \n\t\"Bairro\": \"Jardim Guairaca\", \n\t\"Cidade\": \"São Paulo\",\n\t\"Pais\": null,\n\t\"UF\": \"SP\"\n},\n\"EstadoCivil\": \"Casado\",\n\"Facebook\": \"\",\n\"Foto\": null,\n\"IDProfissao\": \"5ddb346a073d50000448320b\",\n\"Indicacao\": \"\",\n\"Instagram\": \"\",\n\t\"Nome\": \"Ricardo\",\n\"Senha\": \"Senha1234\",\n\"SobreNome\": \"Tao\",\n\"Telefones\": {\n\t\"Tipo\": \"Celular\", \n\t\"Operadora\": \"Claro\", \n\t\"DDD\": \"11\", \n\t\"Numero\": \"991679626\"\n}\n}"},"created":1575211839359,"description":"","headers":[{"id":"pair_79d5039aa8a04d2bbd74ded6a9abf392","name":"Content-Type","value":"application/json"}],"isPrivate":false,"metaSortKey":-1575211839359,"method":"POST","modified":1575212893885,"name":"Adicionar","parameters":[],"parentId":"fld_c31764be2f4e49d1bd2e7d5822370928","settingDisableRenderRequestBody":false,"settingEncodeUrl":true,"settingFollowRedirects":"global","settingRebuildPath":true,"settingSendCookies":true,"settingStoreCookies":true,"url":"{{ base_url_producao  }}Paciente/Adicionar","_type":"request"},{"_id":"fld_c31764be2f4e49d1bd2e7d5822370928","created":1575212640761,"description":"","environment":{},"environmentPropertyOrder":null,"metaSortKey":-1575212640762,"modified":1575212640761,"name":"Paciente","parentId":"wrk_588d05daa95c4c27b18d458ede21e48a","_type":"request_group"},{"_id":"wrk_588d05daa95c4c27b18d458ede21e48a","created":1575211665966,"description":"","modified":1575211665966,"name":"Insomnia","parentId":null,"_type":"workspace"},{"_id":"req_0686cc14cfbe48dfac25a04151d9f541","authentication":{"token":"{{ token  }}","type":"bearer"},"body":{},"created":1575220428770,"description":"","headers":[],"isPrivate":false,"metaSortKey":-1575220428770,"method":"GET","modified":1575220451880,"name":"Listar","parameters":[],"parentId":"fld_c31764be2f4e49d1bd2e7d5822370928","settingDisableRenderRequestBody":false,"settingEncodeUrl":true,"settingFollowRedirects":"global","settingRebuildPath":true,"settingSendCookies":true,"settingStoreCookies":true,"url":"{{ base_url_producao  }}Paciente/Listar","_type":"request"},{"_id":"req_d3a23779ef1045f38cafa4fafd359db2","authentication":{"token":"{{ token  }}","type":"bearer"},"body":{},"created":1575252902720,"description":"","headers":[],"isPrivate":false,"metaSortKey":-1575252902720,"method":"GET","modified":1575252961594,"name":"Listar Nome","parameters":[],"parentId":"fld_c31764be2f4e49d1bd2e7d5822370928","settingDisableRenderRequestBody":false,"settingEncodeUrl":true,"settingFollowRedirects":"global","settingRebuildPath":true,"settingSendCookies":true,"settingStoreCookies":true,"url":"{{ base_url_producao  }}Paciente/ListarNome/ric","_type":"request"},{"_id":"req_e2ec06d5105b4313b8f2c2602e5e811b","authentication":{},"body":{"mimeType":"application/json","text":"{\n\t\"Email\": \"ricardotao@gmail.com\",\n\t\"Senha\": \"123456\"\n}"},"created":1575212405543,"description":"","headers":[{"id":"pair_4009139b30f0425fb1e2f2d4e6764771","name":"Content-Type","value":"application/json"}],"isPrivate":false,"metaSortKey":-1575212405543,"method":"POST","modified":1575212744183,"name":"Login","parameters":[],"parentId":"fld_b4100681fd164c909179529eae94da9a","settingDisableRenderRequestBody":false,"settingEncodeUrl":true,"settingFollowRedirects":"global","settingRebuildPath":true,"settingSendCookies":true,"settingStoreCookies":true,"url":"{{ base_url_producao  }}Autenticacao/Login","_type":"request"},{"_id":"fld_b4100681fd164c909179529eae94da9a","created":1575212650369,"description":"","environment":{},"environmentPropertyOrder":null,"metaSortKey":-1575212661052,"modified":1575212820322,"name":"Login","parentId":"wrk_588d05daa95c4c27b18d458ede21e48a","_type":"request_group"},{"_id":"req_97dc94fdfc404f4792358b1cdd7ae3f4","authentication":{"token":"{{ token  }}","type":"bearer"},"body":{},"created":1575212669589,"description":"","headers":[],"isPrivate":false,"metaSortKey":-1575212669589,"method":"GET","modified":1575235053254,"name":"Listar","parameters":[],"parentId":"fld_675436c077c440aea7d3ec789dd1e74a","settingDisableRenderRequestBody":false,"settingEncodeUrl":true,"settingFollowRedirects":"global","settingRebuildPath":true,"settingSendCookies":true,"settingStoreCookies":true,"url":"{{ base_url_producao  }}Profissao/Listar","_type":"request"},{"_id":"fld_675436c077c440aea7d3ec789dd1e74a","created":1575212661002,"description":"","environment":{},"environmentPropertyOrder":null,"metaSortKey":-1575212661002,"modified":1575212661002,"name":"Profissão","parentId":"wrk_588d05daa95c4c27b18d458ede21e48a","_type":"request_group"},{"_id":"req_cbf2a35c67194e758f65419a72a5a8a2","authentication":{"token":"{{ token  }}","type":"bearer"},"body":{},"created":1575234933004,"description":"","headers":[],"isPrivate":false,"metaSortKey":-1575212669539,"method":"DELETE","modified":1575235676904,"name":"Deletar","parameters":[],"parentId":"fld_675436c077c440aea7d3ec789dd1e74a","settingDisableRenderRequestBody":false,"settingEncodeUrl":true,"settingFollowRedirects":"global","settingRebuildPath":true,"settingSendCookies":true,"settingStoreCookies":true,"url":"{{ base_url_producao  }}Profissao/Deletar/5de40dab450cb80004b912e8","_type":"request"},{"_id":"req_0b12ee7ad55c4004a98a3a3b4f61cce5","authentication":{"token":"{{ token  }}","type":"bearer"},"body":{},"created":1575220325168,"description":"","headers":[],"isPrivate":false,"metaSortKey":-1575220325168,"method":"GET","modified":1575220498729,"name":"Listar","parameters":[],"parentId":"fld_080a6a8b0c624b0da1494f8d8b15a797","settingDisableRenderRequestBody":false,"settingEncodeUrl":true,"settingFollowRedirects":"global","settingRebuildPath":true,"settingSendCookies":true,"settingStoreCookies":true,"url":"{{ base_url_producao  }}Prontuario/Listar/5de3d75f4ac2ac0004e0dece","_type":"request"},{"_id":"fld_080a6a8b0c624b0da1494f8d8b15a797","created":1575220304600,"description":"","environment":{},"environmentPropertyOrder":null,"metaSortKey":-1575212661102,"modified":1575220329547,"name":"Prontuário","parentId":"wrk_588d05daa95c4c27b18d458ede21e48a","_type":"request_group"},{"_id":"req_36b45be7ad474288910a44cb0f48c178","authentication":{},"body":{},"created":1576205506280,"description":"","headers":[],"isPrivate":false,"metaSortKey":-1576205506280,"method":"GET","modified":1576205527066,"name":"My Request","parameters":[],"parentId":"fld_51867b7ab26b4e73ab397704efe00080","settingDisableRenderRequestBody":false,"settingEncodeUrl":true,"settingFollowRedirects":"global","settingRebuildPath":true,"settingSendCookies":true,"settingStoreCookies":true,"url":"https://hora-ponto.herokuapp.com/user/store","_type":"request"},{"_id":"fld_51867b7ab26b4e73ab397704efe00080","created":1576205488659,"description":"","environment":{},"environmentPropertyOrder":null,"metaSortKey":-1576205488660,"modified":1576205488659,"name":"User","parentId":"wrk_7b2cea76f22c4bfca0f33e1a180cdcdf","_type":"request_group"},{"_id":"wrk_7b2cea76f22c4bfca0f33e1a180cdcdf","created":1575734612415,"description":"","modified":1575734612415,"name":"Insomnia","parentId":null,"_type":"workspace"},{"_id":"req_69f10c8b7ae24cceb2c31f4b594a1c57","authentication":{},"body":{"mimeType":"application/json","text":"{\n\t\"UserId\": \"5df45fe5c5bed073edadec33\",\n\t\"Day\": \"2019-12-21T00:00:00.000Z\",\n\t\"Hour\": \"2019-12-21T14:00:00.000Z\",\n\t\"Type\": \"entrada\"\n}"},"created":1576945503590,"description":"","headers":[{"id":"pair_1577e2c3464a422ebfdfa0186f9be4ba","name":"Content-Type","value":"application/json"}],"isPrivate":false,"metaSortKey":-1576945503590,"method":"POST","modified":1576947609382,"name":"POST","parameters":[],"parentId":"fld_18c2bdbf0113431d9822f65c2bf443e1","settingDisableRenderRequestBody":false,"settingEncodeUrl":true,"settingFollowRedirects":"global","settingRebuildPath":true,"settingSendCookies":true,"settingStoreCookies":true,"url":"http://localhost:4000/point/","_type":"request"},{"_id":"fld_18c2bdbf0113431d9822f65c2bf443e1","created":1576945496064,"description":"","environment":{},"environmentPropertyOrder":null,"metaSortKey":-1576945496064,"modified":1576945496064,"name":"Point","parentId":"wrk_56b68c6fd1d6468d9c2ca9377505a843","_type":"request_group"},{"_id":"wrk_56b68c6fd1d6468d9c2ca9377505a843","created":1576945489629,"description":"","modified":1576945489629,"name":"HoraPonto","parentId":null,"_type":"workspace"},{"_id":"req_dc7ad96e9ebc4838b9dac9a404f6e458","authentication":{},"body":{},"created":1576947803197,"description":"","headers":[],"isPrivate":false,"metaSortKey":-1576947803197,"method":"GET","modified":1576947823342,"name":"INDEX","parameters":[],"parentId":"fld_18c2bdbf0113431d9822f65c2bf443e1","settingDisableRenderRequestBody":false,"settingEncodeUrl":true,"settingFollowRedirects":"global","settingRebuildPath":true,"settingSendCookies":true,"settingStoreCookies":true,"url":"http://localhost:4000/point/index/5df45fe5c5bed073edadec33/2019-12-21","_type":"request"},{"_id":"env_09aa4eadc6bdf733f0a1c5a38ba3f7ff4f67e9e8","color":null,"created":1575211666224,"data":{"base_url_producao":"https://quiro-app.herokuapp.com/","token":"eyJhbGciOiJIUzI1NiIsInR5cCI6IkpXVCJ9.eyJpZCI6IjVkYjVhZTZhYzRhN2JhMDAwNGMyZDFhYSIsImlhdCI6MTU3NjI5MzQwMywiZXhwIjoxNTc2Mzc5ODAzfQ.0D5bJFhK3ppEDnFx3l5-75WUpyvB7DZFxiZUFpwYAbU"},"dataPropertyOrder":{"&":["base_url_producao","token"]},"isPrivate":false,"metaSortKey":1575211666224,"modified":1576293444068,"name":"Base Environment","parentId":"wrk_588d05daa95c4c27b18d458ede21e48a","_type":"environment"},{"_id":"jar_09aa4eadc6bdf733f0a1c5a38ba3f7ff4f67e9e8","cookies":[],"created":1575211666228,"modified":1575211666228,"name":"Default Jar","parentId":"wrk_588d05daa95c4c27b18d458ede21e48a","_type":"cookie_jar"},{"_id":"env_a65ca8e3db15001f5ae7426102c26fef5e384db5","color":null,"created":1575734612522,"data":{},"dataPropertyOrder":null,"isPrivate":false,"metaSortKey":1575734612522,"modified":1575734612522,"name":"Base Environment","parentId":"wrk_7b2cea76f22c4bfca0f33e1a180cdcdf","_type":"environment"},{"_id":"jar_a65ca8e3db15001f5ae7426102c26fef5e384db5","cookies":[],"created":1575734612528,"modified":1575734612528,"name":"Default Jar","parentId":"wrk_7b2cea76f22c4bfca0f33e1a180cdcdf","_type":"cookie_jar"},{"_id":"env_c5163fb6212450607d52e7345e228043d5d83889","color":null,"created":1576945489698,"data":{},"dataPropertyOrder":null,"isPrivate":false,"metaSortKey":1576945489698,"modified":1576945489698,"name":"Base Environment","parentId":"wrk_56b68c6fd1d6468d9c2ca9377505a843","_type":"environment"},{"_id":"jar_c5163fb6212450607d52e7345e228043d5d83889","cookies":[],"created":1576945489701,"modified":1576945489701,"name":"Default Jar","parentId":"wrk_56b68c6fd1d6468d9c2ca9377505a843","_type":"cookie_jar"}]}